{
  "name": "Hive Backend",
  "uid": "NuARlJoAWtjrOlZrJ5yhb",
  "version": "1",
  "items": [
    {
      "uid": "VFDzXQaQ0opteck3kwZeS",
      "name": "App",
      "type": "folder",
      "root": {
        "request": {
          "auth": {
            "mode": "inherit",
            "basic": null,
            "bearer": null,
            "digest": null,
            "apikey": null,
            "oauth2": null
          }
        },
        "meta": {
          "name": "App"
        }
      },
      "items": [
        {
          "uid": "0jOieGfZvWGueT1V114rM",
          "name": "AppController_getHello",
          "type": "http-request",
          "request": {
            "url": "{{baseUrl}}/",
            "method": "GET",
            "auth": {
              "mode": "inherit",
              "basic": null,
              "bearer": null,
              "digest": null,
              "apikey": null,
              "oauth2": null
            },
            "headers": [],
            "params": [],
            "body": {
              "mode": "none",
              "json": null,
              "text": null,
              "xml": null,
              "formUrlEncoded": [],
              "multipartForm": []
            },
            "script": {
              "res": null
            }
          },
          "examples": [
            {
              "uid": "iYnZssOjFhA6BuUtAgAHE",
              "itemUid": "0jOieGfZvWGueT1V114rM",
              "name": "200 Response",
              "description": "",
              "type": "http-request",
              "request": {
                "url": "{{baseUrl}}/",
                "method": "GET",
                "headers": [],
                "params": [],
                "body": {
                  "mode": "none",
                  "json": null,
                  "text": null,
                  "xml": null,
                  "formUrlEncoded": [],
                  "multipartForm": []
                }
              },
              "response": {
                "status": "200",
                "statusText": "OK",
                "headers": [],
                "body": {
                  "type": "text",
                  "content": ""
                }
              }
            }
          ],
          "seq": 1
        }
      ]
    },
    {
      "uid": "juligwLFSp3YWi18ko0Zb",
      "name": "AI",
      "type": "folder",
      "root": {
        "request": {
          "auth": {
            "mode": "inherit",
            "basic": null,
            "bearer": null,
            "digest": null,
            "apikey": null,
            "oauth2": null
          }
        },
        "meta": {
          "name": "AI"
        }
      },
      "items": [
        {
          "uid": "GH25Z9LxOHuZK8yNxBt8P",
          "name": "Extract plan details from an uploaded file",
          "type": "http-request",
          "request": {
            "url": "{{baseUrl}}/ai/extract-plan",
            "method": "POST",
            "auth": {
              "mode": "inherit",
              "basic": null,
              "bearer": null,
              "digest": null,
              "apikey": null,
              "oauth2": null
            },
            "headers": [],
            "params": [],
            "body": {
              "mode": "multipartForm",
              "json": null,
              "text": null,
              "xml": null,
              "formUrlEncoded": [],
              "multipartForm": [
                {
                  "uid": "u1LAI4OAl6kkOh6OjJH3c",
                  "type": "text",
                  "name": "file",
                  "value": "",
                  "description": "",
                  "enabled": true
                }
              ]
            },
            "script": {
              "res": null
            }
          },
          "examples": [
            {
              "uid": "BvF8qvkQ3WksHUkkuEJZ5",
              "itemUid": "GH25Z9LxOHuZK8yNxBt8P",
              "name": "201 Response",
              "description": "Extracted plan details",
              "type": "http-request",
              "request": {
                "url": "{{baseUrl}}/ai/extract-plan",
                "method": "POST",
                "headers": [],
                "params": [],
                "body": {
                  "mode": "multipartForm",
                  "json": null,
                  "text": null,
                  "xml": null,
                  "formUrlEncoded": [],
                  "multipartForm": [
                    {
                      "uid": "u1LAI4OAl6kkOh6OjJH3c",
                      "type": "text",
                      "name": "file",
                      "value": "",
                      "description": "",
                      "enabled": true
                    }
                  ]
                }
              },
              "response": {
                "status": "201",
                "statusText": "Created",
                "headers": [
                  {
                    "uid": "WtCJ2jD5r6sM6r1AZjFXn",
                    "name": "Content-Type",
                    "value": "application/json",
                    "description": "",
                    "enabled": true
                  }
                ],
                "body": {
                  "type": "json",
                  "content": "{\n  \"customer\": \"\",\n  \"price\": 0,\n  \"weight\": 0,\n  \"pickupPoint\": \"\",\n  \"pickupTime\": \"\",\n  \"dropoffPoint\": \"\",\n  \"dropoffTime\": \"\",\n  \"description\": \"\"\n}"
                }
              }
            }
          ],
          "seq": 1
        }
      ]
    }
  ],
  "environments": [],
  "root": {
    "request": {
      "auth": {
        "mode": "none",
        "basic": null,
        "bearer": null,
        "digest": null,
        "apikey": null,
        "oauth2": null
      }
    },
    "meta": {
      "name": "Hive Backend"
    }
  }
}